<?xml version="1.0" encoding="UTF-8" ?>
<legge190:pubblicazione
	xsi:schemaLocation="legge190_1_0 datasetAppaltiL190.xsd"
	xmlns:xsi="http://www.w3.org/2001/XMLSchema-instance"
	xmlns:legge190="legge190_1_0">
	<metadata>
		<titolo> Pubblicazione legge 190</titolo>
		<abstract>Pubblicazione legge 190 anno 1 rif. 2016</abstract>
		<dataPubbicazioneDataset>2016-01-26</dataPubbicazioneDataset>
		<entePubblicatore>Comune di Dolzago</entePubblicatore>
		<dataUltimoAggiornamentoDataset>2017-02-20</dataUltimoAggiornamentoDataset>
		<annoRiferimento>2016</annoRiferimento>
		<urlFile>http://www.halleyweb.com/c097031/zf/index.php/dataset/appalti-2016.xml</urlFile>
		<licenza>IODL</licenza>
	</metadata>
	<data>
					<lotto>
				<cig>Z137A7D15</cig>
		<strutturaProponente>
			<codiceFiscaleProp>00624600136</codiceFiscaleProp>
			<denominazione>COMUNE DI DOLZAGO</denominazione>
		</strutturaProponente>
		<oggetto>ACQUISTO AUTOCARRO PROTEZIONE CIVILE</oggetto>
		<sceltaContraente>23-AFFIDAMENTO IN ECONOMIA - AFFIDAMENTO DIRETTO</sceltaContraente>
		<partecipanti>
									    			    				        
					<partecipante>					   
					                                <codiceFiscale>00837340140</codiceFiscale>
                        						<ragioneSociale>AGRIFORNITURE BARRI SNC</ragioneSociale>
											</partecipante>	
													</partecipanti>
		<aggiudicatari>
								</aggiudicatari>
		<importoAggiudicazione>0.00</importoAggiudicazione>
		<tempiCompletamento>
								</tempiCompletamento>
		<importoSommeLiquidate>0.00</importoSommeLiquidate>
	</lotto>
			<lotto>
				<cig>Z611919D2</cig>
		<strutturaProponente>
			<codiceFiscaleProp>00624600136</codiceFiscaleProp>
			<denominazione>COMUNE DI DOLZAGO</denominazione>
		</strutturaProponente>
		<oggetto>IMPEGNO DI SPESA PER CONCIMAZIONE CAMPO CALCIO</oggetto>
		<sceltaContraente>23-AFFIDAMENTO IN ECONOMIA - AFFIDAMENTO DIRETTO</sceltaContraente>
		<partecipanti>
									    			    				        
					<partecipante>					   
					                                <codiceFiscale>01400130132</codiceFiscale>
                        						<ragioneSociale>GAMMA VERDE S.R.L.</ragioneSociale>
											</partecipante>	
													</partecipanti>
		<aggiudicatari>
						    			    			    		    	<aggiudicatario>    					                            <codiceFiscale>01400130132</codiceFiscale>
                        	
    					<ragioneSociale>GAMMA VERDE SRL</ragioneSociale>
    					    				</aggiudicatario>    			    								</aggiudicatari>
		<importoAggiudicazione>612.56</importoAggiudicazione>
		<tempiCompletamento>
							<dataInizio>2016-03-25</dataInizio>
										<dataUltimazione>2016-12-31</dataUltimazione>
					</tempiCompletamento>
		<importoSommeLiquidate>612.56</importoSommeLiquidate>
	</lotto>
			<lotto>
				<cig>Z4D1A79FDA</cig>
		<strutturaProponente>
			<codiceFiscaleProp>00624600136</codiceFiscaleProp>
			<denominazione>COMUNE DI DOLZAGO</denominazione>
		</strutturaProponente>
		<oggetto>IMPEGNO DI SPESA PER ALLACCIAMENTO IDRICO DA ESEGUIRSI IN VIA DANTE</oggetto>
		<sceltaContraente>23-AFFIDAMENTO IN ECONOMIA - AFFIDAMENTO DIRETTO</sceltaContraente>
		<partecipanti>
									    			    				        
					<partecipante>					   
					                                <codiceFiscale>03119540130</codiceFiscale>
                        						<ragioneSociale>LARIO RETI HOLDING SPA</ragioneSociale>
											</partecipante>	
													</partecipanti>
		<aggiudicatari>
						    			    			    		    	<aggiudicatario>    					                            <codiceFiscale>03119540130</codiceFiscale>
                        	
    					<ragioneSociale>LARIO RETI HOLDING S.P.A.</ragioneSociale>
    					    				</aggiudicatario>    			    								</aggiudicatari>
		<importoAggiudicazione>1519.85</importoAggiudicazione>
		<tempiCompletamento>
							<dataInizio>2016-06-28</dataInizio>
										<dataUltimazione>2016-12-31</dataUltimazione>
					</tempiCompletamento>
		<importoSommeLiquidate>1671.84</importoSommeLiquidate>
	</lotto>
			<lotto>
				<cig>6714605B53</cig>
		<strutturaProponente>
			<codiceFiscaleProp>00624600136</codiceFiscaleProp>
			<denominazione>COMUNE DI DOLZAGO</denominazione>
		</strutturaProponente>
		<oggetto>PRESA D'ATTO AGGIUDICAZIONE DEFINITIVA SUA PROVINCIA DI LECCO LAVORI PER LA REALIZZAZIONE DELL'INTERVENTO DI MIGLIORAMENTO ANTISISMICO SCUOLA PRIMARIA</oggetto>
		<sceltaContraente>06-PROCEDURA NEGOZIATA SENZA PREVIA INDIZIONE DI  GARA ART. 221 D.LGS. 163/2006</sceltaContraente>
		<partecipanti>
									    			    				        
					<partecipante>					   
					                                <codiceFiscale>01004480172</codiceFiscale>
                        						<ragioneSociale>SP.A.M. SRL</ragioneSociale>
											</partecipante>	
													</partecipanti>
		<aggiudicatari>
						    			    			    		    	<aggiudicatario>    					                            <codiceFiscale>01004480172</codiceFiscale>
                        	
    					<ragioneSociale>SP.A.M.</ragioneSociale>
    					    				</aggiudicatario>    			    								</aggiudicatari>
		<importoAggiudicazione>251729.78</importoAggiudicazione>
		<tempiCompletamento>
							<dataInizio>2016-07-28</dataInizio>
										<dataUltimazione>2016-12-31</dataUltimazione>
					</tempiCompletamento>
		<importoSommeLiquidate>0.00</importoSommeLiquidate>
	</lotto>
			<lotto>
				<cig>Z461AB97B1</cig>
		<strutturaProponente>
			<codiceFiscaleProp>00624600136</codiceFiscaleProp>
			<denominazione>COMUNE DI DOLZAGO</denominazione>
		</strutturaProponente>
		<oggetto>IMPEGNO DI SPESA PER AFFIDAMENTO COLLAUDO STATICO INTERVENTO MIGLIORAMENTO ANTISMICO SCUOLA PRIMARIA</oggetto>
		<sceltaContraente>23-AFFIDAMENTO IN ECONOMIA - AFFIDAMENTO DIRETTO</sceltaContraente>
		<partecipanti>
									    			    				        
					<partecipante>					   
					                                <codiceFiscale>02253210138</codiceFiscale>
                        						<ragioneSociale>ING. ALBERTO INVERNIZZI</ragioneSociale>
											</partecipante>	
													</partecipanti>
		<aggiudicatari>
						    			    			    		    	<aggiudicatario>    					                            <codiceFiscale>02253210138</codiceFiscale>
                        	
    					<ragioneSociale>ING. ALBERTO INVERNIZZI</ragioneSociale>
    					    				</aggiudicatario>    			    								</aggiudicatari>
		<importoAggiudicazione>1979.33</importoAggiudicazione>
		<tempiCompletamento>
							<dataInizio>2016-08-01</dataInizio>
										<dataUltimazione>2017-01-01</dataUltimazione>
					</tempiCompletamento>
		<importoSommeLiquidate>0.00</importoSommeLiquidate>
	</lotto>
			<lotto>
				<cig>ZEF1AD224A</cig>
		<strutturaProponente>
			<codiceFiscaleProp>00624600136</codiceFiscaleProp>
			<denominazione>COMUNE DI DOLZAGO</denominazione>
		</strutturaProponente>
		<oggetto>IMPEGNO DI SPESA PER AFFIDAMENTO STUDIO DI FATTIBILITA' TECNICA ED ECONOMICA LAVORI CIMITERIALI</oggetto>
		<sceltaContraente>23-AFFIDAMENTO IN ECONOMIA - AFFIDAMENTO DIRETTO</sceltaContraente>
		<partecipanti>
									    			    				        
					<partecipante>					   
					                                <codiceFiscale>03115310132</codiceFiscale>
                        						<ragioneSociale>GEOM. RIVA GABRIELE</ragioneSociale>
											</partecipante>	
													</partecipanti>
		<aggiudicatari>
						    			    			    		    	<aggiudicatario>    					                            <codiceFiscale>03115310132</codiceFiscale>
                        	
    					<ragioneSociale>RIVA Gabriele</ragioneSociale>
    					    				</aggiudicatario>    			    								</aggiudicatari>
		<importoAggiudicazione>1450.00</importoAggiudicazione>
		<tempiCompletamento>
							<dataInizio>2016-08-02</dataInizio>
										<dataUltimazione>2016-12-31</dataUltimazione>
					</tempiCompletamento>
		<importoSommeLiquidate>0.00</importoSommeLiquidate>
	</lotto>
			<lotto>
				<cig>ZA71C7C4AC</cig>
		<strutturaProponente>
			<codiceFiscaleProp>00624600136</codiceFiscaleProp>
			<denominazione>COMUNE DI DOLZAGO</denominazione>
		</strutturaProponente>
		<oggetto>RELAZIONE IDRAULICA E DETTAGLIO COSTRUTTIVO SCARICO ACQUE METEORCIHE - IMPEGNO DI SPESA</oggetto>
		<sceltaContraente>23-AFFIDAMENTO IN ECONOMIA - AFFIDAMENTO DIRETTO</sceltaContraente>
		<partecipanti>
									    			    				        
					<partecipante>					   
					                                <codiceFiscale>02253210138</codiceFiscale>
                        						<ragioneSociale>ING. ALBERTO INVERNIZZI</ragioneSociale>
											</partecipante>	
													</partecipanti>
		<aggiudicatari>
						    			    			    		    	<aggiudicatario>    					                            <codiceFiscale>02253210138</codiceFiscale>
                        	
    					<ragioneSociale>INVERNIZZI Alberto</ragioneSociale>
    					    				</aggiudicatario>    			    								</aggiudicatari>
		<importoAggiudicazione>550.00</importoAggiudicazione>
		<tempiCompletamento>
							<dataInizio>2016-12-15</dataInizio>
										<dataUltimazione>2017-02-28</dataUltimazione>
					</tempiCompletamento>
		<importoSommeLiquidate>0.00</importoSommeLiquidate>
	</lotto>
			<lotto>
				<cig>Z641C7B97A</cig>
		<strutturaProponente>
			<codiceFiscaleProp>00624600136</codiceFiscaleProp>
			<denominazione>COMUNE DI DOLZAGO</denominazione>
		</strutturaProponente>
		<oggetto>SOSTITUZIONE LAMPADE SCUOLA PRIMARIA - IMPEGNO DI SPESA</oggetto>
		<sceltaContraente>23-AFFIDAMENTO IN ECONOMIA - AFFIDAMENTO DIRETTO</sceltaContraente>
		<partecipanti>
									    			    				        
					<partecipante>					   
					                                <codiceFiscale>00377690136</codiceFiscale>
                        						<ragioneSociale>FRATELLI BONFANTI SNC</ragioneSociale>
											</partecipante>	
													</partecipanti>
		<aggiudicatari>
						    			    			    		    	<aggiudicatario>    					                            <codiceFiscale>00377690136</codiceFiscale>
                        	
    					<ragioneSociale>FRATELLI BONFANTI SNC</ragioneSociale>
    					    				</aggiudicatario>    			    								</aggiudicatari>
		<importoAggiudicazione>13636.36</importoAggiudicazione>
		<tempiCompletamento>
							<dataInizio>2016-12-15</dataInizio>
										<dataUltimazione>2017-01-05</dataUltimazione>
					</tempiCompletamento>
		<importoSommeLiquidate>0.00</importoSommeLiquidate>
	</lotto>
			<lotto>
				<cig>Z5B1C7C8B3</cig>
		<strutturaProponente>
			<codiceFiscaleProp>00624600136</codiceFiscaleProp>
			<denominazione>COMUNE DI DOLZAGO</denominazione>
		</strutturaProponente>
		<oggetto>SERVIZIO MANUTENZIONE IMPIANTI ILLUMINAZIONE PUBBLICA - ANNO 2017</oggetto>
		<sceltaContraente>23-AFFIDAMENTO IN ECONOMIA - AFFIDAMENTO DIRETTO</sceltaContraente>
		<partecipanti>
									    			    				        
					<partecipante>					   
					                                <codiceFiscale>00377690136</codiceFiscale>
                        						<ragioneSociale>FRATELLI BONFANTI SNC</ragioneSociale>
											</partecipante>	
													</partecipanti>
		<aggiudicatari>
						    			    			    		    	<aggiudicatario>    					                            <codiceFiscale>00377690136</codiceFiscale>
                        	
    					<ragioneSociale>FRATELLI BONFANTI SNC</ragioneSociale>
    					    				</aggiudicatario>    			    								</aggiudicatari>
		<importoAggiudicazione>38500.00</importoAggiudicazione>
		<tempiCompletamento>
							<dataInizio>2016-12-15</dataInizio>
										<dataUltimazione>2017-12-31</dataUltimazione>
					</tempiCompletamento>
		<importoSommeLiquidate>0.00</importoSommeLiquidate>
	</lotto>
			<lotto>
				<cig>Z181CC2410</cig>
		<strutturaProponente>
			<codiceFiscaleProp>00624600136</codiceFiscaleProp>
			<denominazione>COMUNE DI DOLZAGO</denominazione>
		</strutturaProponente>
		<oggetto>SOSTITUZIONE TESTINA STAMPANTE EPSON FX 2190 UFFICIO ANAGRAFE - IMPEGNO DI SPESA</oggetto>
		<sceltaContraente>23-AFFIDAMENTO IN ECONOMIA - AFFIDAMENTO DIRETTO</sceltaContraente>
		<partecipanti>
									    			    				        
					<partecipante>					   
					                                <codiceFiscale>01355000132</codiceFiscale>
                        						<ragioneSociale>BCS SRL</ragioneSociale>
											</partecipante>	
													</partecipanti>
		<aggiudicatari>
						    			    			    		    	<aggiudicatario>    					                            <codiceFiscale>01355000132</codiceFiscale>
                        	
    					<ragioneSociale>BCS SRL</ragioneSociale>
    					    				</aggiudicatario>    			    								</aggiudicatari>
		<importoAggiudicazione>115.00</importoAggiudicazione>
		<tempiCompletamento>
							<dataInizio>2016-12-22</dataInizio>
										<dataUltimazione>2017-12-31</dataUltimazione>
					</tempiCompletamento>
		<importoSommeLiquidate>0.00</importoSommeLiquidate>
	</lotto>
			<lotto>
				<cig>Z201CC5643</cig>
		<strutturaProponente>
			<codiceFiscaleProp>00624600136</codiceFiscaleProp>
			<denominazione>COMUNE DI DOLZAGO</denominazione>
		</strutturaProponente>
		<oggetto>FORNITURA EQUIPAGGIAMENTO PROTEZIONE CIVILE - IMPEGNO DI SPESA</oggetto>
		<sceltaContraente>23-AFFIDAMENTO IN ECONOMIA - AFFIDAMENTO DIRETTO</sceltaContraente>
		<partecipanti>
									    			    				        
					<partecipante>					   
					                                <codiceFiscale>01960610135</codiceFiscale>
                        						<ragioneSociale>SECURTRADING SAS</ragioneSociale>
											</partecipante>	
													</partecipanti>
		<aggiudicatari>
						    			    			    		    	<aggiudicatario>    					                            <codiceFiscale>00000000000</codiceFiscale>
                        	
    					<ragioneSociale>SECURTRADING SAS DI OLIVIERI</ragioneSociale>
    					    				</aggiudicatario>    			    								</aggiudicatari>
		<importoAggiudicazione>3660.00</importoAggiudicazione>
		<tempiCompletamento>
							<dataInizio>2016-12-30</dataInizio>
										<dataUltimazione>2016-12-31</dataUltimazione>
					</tempiCompletamento>
		<importoSommeLiquidate>0.00</importoSommeLiquidate>
	</lotto>
			<lotto>
				<cig>ZAE1CB75C5</cig>
		<strutturaProponente>
			<codiceFiscaleProp>00624600136</codiceFiscaleProp>
			<denominazione>COMUNE DI DOLZAGO</denominazione>
		</strutturaProponente>
		<oggetto>INTERVENTI DI MANUTENZIONE TORRENTE GANDALOGLIO</oggetto>
		<sceltaContraente>23-AFFIDAMENTO IN ECONOMIA - AFFIDAMENTO DIRETTO</sceltaContraente>
		<partecipanti>
									    			    				        
					<partecipante>					   
					                                <codiceFiscale>01500900137</codiceFiscale>
                        						<ragioneSociale>Redaelli Francesco s.r.l.</ragioneSociale>
											</partecipante>	
													</partecipanti>
		<aggiudicatari>
						    			    			    		    	<aggiudicatario>    					                            <codiceFiscale>01500900137</codiceFiscale>
                        	
    					<ragioneSociale>Redaelli Francesco s.r.l.</ragioneSociale>
    					    				</aggiudicatario>    			    								</aggiudicatari>
		<importoAggiudicazione>17604.60</importoAggiudicazione>
		<tempiCompletamento>
							<dataInizio>2016-12-30</dataInizio>
										<dataUltimazione>2017-12-31</dataUltimazione>
					</tempiCompletamento>
		<importoSommeLiquidate>0.00</importoSommeLiquidate>
	</lotto>
			<lotto>
				<cig>Z211862480</cig>
		<strutturaProponente>
			<codiceFiscaleProp>00624600136</codiceFiscaleProp>
			<denominazione>COMUNE DI DOLZAGO</denominazione>
		</strutturaProponente>
		<oggetto>SERVIZIO INSERIMENTO DISABILE IN COMUNITA' - ANNO 2016</oggetto>
		<sceltaContraente>23-AFFIDAMENTO IN ECONOMIA - AFFIDAMENTO DIRETTO</sceltaContraente>
		<partecipanti>
									    			    				        
					<partecipante>					   
					                                <codiceFiscale>02595400587</codiceFiscale>
                        						<ragioneSociale>CASA DI GINO OPERA DON GUANELLA</ragioneSociale>
											</partecipante>	
													</partecipanti>
		<aggiudicatari>
						    			    			    		    	<aggiudicatario>    					                            <codiceFiscale>02595400587</codiceFiscale>
                        	
    					<ragioneSociale>CASA DI GINO OPERA DON GUANELLA</ragioneSociale>
    					    				</aggiudicatario>    			    								</aggiudicatari>
		<importoAggiudicazione>33893.64</importoAggiudicazione>
		<tempiCompletamento>
							<dataInizio>2016-01-01</dataInizio>
										<dataUltimazione>2016-12-31</dataUltimazione>
					</tempiCompletamento>
		<importoSommeLiquidate>30794.70</importoSommeLiquidate>
	</lotto>
			<lotto>
				<cig>ZEF19C24EE</cig>
		<strutturaProponente>
			<codiceFiscaleProp>00624600136</codiceFiscaleProp>
			<denominazione>COMUNE DI DOLZAGO</denominazione>
		</strutturaProponente>
		<oggetto>IMPEGNO DI SPESA PER CONVENZIONE CON I CAAF PER SERVIZIO ISEE- ASSEGNI DI MATERNITA' E NUCLEO NUMEROSO - SISTEMA SGATE (BONUS ENERGIA, BONUS GAS) - ANNO 2016</oggetto>
		<sceltaContraente>23-AFFIDAMENTO IN ECONOMIA - AFFIDAMENTO DIRETTO</sceltaContraente>
		<partecipanti>
									    			    				        
					<partecipante>					   
					                                <codiceFiscale>02282990965</codiceFiscale>
                        						<ragioneSociale>CAAF CGIL LOMBARDIA</ragioneSociale>
											</partecipante>	
								        
					<partecipante>					   
					                                <codiceFiscale>00647550144</codiceFiscale>
                        						<ragioneSociale>CSF SONDRIO LECCO SRL</ragioneSociale>
											</partecipante>	
								        
					<partecipante>					   
					                                <codiceFiscale>02429240134</codiceFiscale>
                        						<ragioneSociale>UIL SERVICE LECCO</ragioneSociale>
											</partecipante>	
													</partecipanti>
		<aggiudicatari>
						    			    			    		    	<aggiudicatario>    					                            <codiceFiscale>02282990965</codiceFiscale>
                        	
    					<ragioneSociale>CAAF CGIL LOMBARDIA</ragioneSociale>
    					    				</aggiudicatario>    			    		    	<aggiudicatario>    					                            <codiceFiscale>00647550144</codiceFiscale>
                        	
    					<ragioneSociale>CSF SONDRIO LECCO SRL</ragioneSociale>
    					    				</aggiudicatario>    			    		    	<aggiudicatario>    					                            <codiceFiscale>02429240134</codiceFiscale>
                        	
    					<ragioneSociale>UIL SERVICE LECCO</ragioneSociale>
    					    				</aggiudicatario>    			    								</aggiudicatari>
		<importoAggiudicazione>1000.00</importoAggiudicazione>
		<tempiCompletamento>
							<dataInizio>2016-01-01</dataInizio>
										<dataUltimazione>2016-12-31</dataUltimazione>
					</tempiCompletamento>
		<importoSommeLiquidate>0.00</importoSommeLiquidate>
	</lotto>
			<lotto>
				<cig>ZA21AC2239</cig>
		<strutturaProponente>
			<codiceFiscaleProp>00624600136</codiceFiscaleProp>
			<denominazione>COMUNE DI DOLZAGO</denominazione>
		</strutturaProponente>
		<oggetto>SERVIZIO DI POSTALIZZAZIONE PER RUOLO T.A.R.I. ANNO 2016</oggetto>
		<sceltaContraente>23-AFFIDAMENTO IN ECONOMIA - AFFIDAMENTO DIRETTO</sceltaContraente>
		<partecipanti>
									    			    				        
					<partecipante>					   
					                                <codiceFiscale>01343230130</codiceFiscale>
                        						<ragioneSociale>HALLEY LOMBARDIA SNC</ragioneSociale>
											</partecipante>	
													</partecipanti>
		<aggiudicatari>
						    			    			    		    	<aggiudicatario>    					                            <codiceFiscale>01343230130</codiceFiscale>
                        	
    					<ragioneSociale>HALLEY Lombardia Snc di Monti Gianpiero, Molteni Mauro</ragioneSociale>
    					    				</aggiudicatario>    			    								</aggiudicatari>
		<importoAggiudicazione>891.33</importoAggiudicazione>
		<tempiCompletamento>
							<dataInizio>2016-01-01</dataInizio>
										<dataUltimazione>2016-12-31</dataUltimazione>
					</tempiCompletamento>
		<importoSommeLiquidate>0.00</importoSommeLiquidate>
	</lotto>
			<lotto>
				<cig>Z5C1A53B2E</cig>
		<strutturaProponente>
			<codiceFiscaleProp>00624600136</codiceFiscaleProp>
			<denominazione>COMUNE DI DOLZAGO</denominazione>
		</strutturaProponente>
		<oggetto>IMPEGNO DI SPESA PER COPERTURA ASSICURATIVA INFORTUNI PER &quot;PROGETTO FARESTATE 2016&quot;</oggetto>
		<sceltaContraente>23-AFFIDAMENTO IN ECONOMIA - AFFIDAMENTO DIRETTO</sceltaContraente>
		<partecipanti>
									    			    				        
					<partecipante>					   
					                                <codiceFiscale>11234220157</codiceFiscale>
                        						<ragioneSociale>LIBRA BROKER</ragioneSociale>
											</partecipante>	
													</partecipanti>
		<aggiudicatari>
						    			    			    		    	<aggiudicatario>    					                            <codiceFiscale>11234220157</codiceFiscale>
                        	
    					<ragioneSociale>Libra Broker di Giovanni B. Liberato</ragioneSociale>
    					    				</aggiudicatario>    			    								</aggiudicatari>
		<importoAggiudicazione>450.00</importoAggiudicazione>
		<tempiCompletamento>
							<dataInizio>2016-06-17</dataInizio>
										<dataUltimazione>2016-07-31</dataUltimazione>
					</tempiCompletamento>
		<importoSommeLiquidate>0.00</importoSommeLiquidate>
	</lotto>
			<lotto>
				<cig>ZAD187D658</cig>
		<strutturaProponente>
			<codiceFiscaleProp>00624600136</codiceFiscaleProp>
			<denominazione>COMUNE DI DOLZAGO</denominazione>
		</strutturaProponente>
		<oggetto>IMPEGNO DI SPESA PER ADEMPIMENTI SPLIT PAYMENT - ANNO 2016</oggetto>
		<sceltaContraente>23-AFFIDAMENTO IN ECONOMIA - AFFIDAMENTO DIRETTO</sceltaContraente>
		<partecipanti>
									    			    				        
					<partecipante>					   
					                                <codiceFiscale>02099950467</codiceFiscale>
                        						<ragioneSociale>ESSE IN SRL</ragioneSociale>
											</partecipante>	
													</partecipanti>
		<aggiudicatari>
						    			    			    		    	<aggiudicatario>    					                            <codiceFiscale>02099950467</codiceFiscale>
                        	
    					<ragioneSociale>ESSE IN SRL</ragioneSociale>
    					    				</aggiudicatario>    			    								</aggiudicatari>
		<importoAggiudicazione>1320.00</importoAggiudicazione>
		<tempiCompletamento>
							<dataInizio>2016-01-01</dataInizio>
										<dataUltimazione>2016-12-31</dataUltimazione>
					</tempiCompletamento>
		<importoSommeLiquidate>0.00</importoSommeLiquidate>
	</lotto>
	</data>
</legge190:pubblicazione>